nonebot_plugin_gsmaterial/__init__.py
nonebot_plugin_gsmaterial/config.py
nonebot_plugin_gsmaterial/data_source.py
nonebot_plugin_gsmaterial/material_draw.py
nonebot_plugin_gsmaterial-0.2.7.dist-info/LICENSE
nonebot_plugin_gsmaterial-0.2.7.dist-info/METADATA
nonebot_plugin_gsmaterial-0.2.7.dist-info/WHEEL
nonebot_plugin_gsmaterial-0.2.7.dist-info/RECORD
